examples/basic_test.py
examples/custom_client.py
examples/custom_reporter.py
examples/multiengine.py
hyperscale/__init__.py
hyperscale/graph.py
hyperscale/plugin.py
hyperscale/testing.py
hyperscale/commands/__init__.py
hyperscale/commands/new.py
hyperscale/commands/ping.py
hyperscale/commands/root.py
hyperscale/commands/run.py
hyperscale/commands/cli/__init__.py
hyperscale/commands/cli/cli.py
hyperscale/commands/cli/cli_protocol.py
hyperscale/commands/cli/command.py
hyperscale/commands/cli/group.py
hyperscale/commands/cli/inspect_wrapped.py
hyperscale/commands/cli/arg_types/__init__.py
hyperscale/commands/cli/arg_types/base/__init__.py
hyperscale/commands/cli/arg_types/base/keyword_arg.py
hyperscale/commands/cli/arg_types/base/positional_arg.py
hyperscale/commands/cli/arg_types/data_types/__init__.py
hyperscale/commands/cli/arg_types/data_types/assert_set.py
hyperscale/commands/cli/arg_types/data_types/context.py
hyperscale/commands/cli/arg_types/data_types/env.py
hyperscale/commands/cli/arg_types/data_types/import_file.py
hyperscale/commands/cli/arg_types/data_types/json_data.py
hyperscale/commands/cli/arg_types/data_types/json_file.py
hyperscale/commands/cli/arg_types/data_types/paths.py
hyperscale/commands/cli/arg_types/data_types/pattern.py
hyperscale/commands/cli/arg_types/data_types/raw_file.py
hyperscale/commands/cli/arg_types/data_types/reduce_pattern_type.py
hyperscale/commands/cli/arg_types/operators/__init__.py
hyperscale/commands/cli/arg_types/operators/chain.py
hyperscale/commands/cli/arg_types/operators/map.py
hyperscale/commands/cli/arg_types/operators/operator.py
hyperscale/commands/cli/help_message/__init__.py
hyperscale/commands/cli/help_message/cli_style.py
hyperscale/commands/cli/help_message/create_help_string.py
hyperscale/commands/cli/help_message/description_help_message.py
hyperscale/commands/cli/help_message/help_message.py
hyperscale/commands/cli/help_message/line_parsing.py
hyperscale/commands/cli/help_message/options_help_message.py
hyperlight_hyperscale-0.5.5.dist-info/LICENSE
hyperlight_hyperscale-0.5.5.dist-info/METADATA
hyperlight_hyperscale-0.5.5.dist-info/WHEEL
hyperlight_hyperscale-0.5.5.dist-info/entry_points.txt
hyperlight_hyperscale-0.5.5.dist-info/top_level.txt
hyperlight_hyperscale-0.5.5.dist-info/RECORD
