Metadata-Version: 2.2
Name: hyperlight-hyperscale
Version: 0.5.5
Summary: Performance testing at scale.
Author-email: Ada Lundhe <sean.corbett@umconnect.edu>
License: MIT License
Project-URL: Homepage, https://github.com/hyper-light/hyperscale
Keywords: pypi,cicd,python,performance,testing,dag,graph,workflow
Classifier: Programming Language :: Python :: 3.11
Classifier: Programming Language :: Python :: 3.12
Classifier: Programming Language :: Python :: 3.13
Classifier: License :: OSI Approved :: MIT License
Classifier: Operating System :: OS Independent
Requires-Python: >=3.11
License-File: LICENSE
Requires-Dist: attr
Requires-Dist: networkx
Requires-Dist: aiodns
Requires-Dist: psutil
Requires-Dist: pydantic
Requires-Dist: zstandard
Requires-Dist: cryptography
Requires-Dist: python-dotenv
Requires-Dist: aioquic
Requires-Dist: cloudpickle
Requires-Dist: orjson
Requires-Dist: msgspec
Requires-Dist: numpy
Provides-Extra: all
Requires-Dist: grpcio; extra == "all"
Requires-Dist: grpcio-tools; extra == "all"
Requires-Dist: gql; extra == "all"
Requires-Dist: playwright; extra == "all"
Requires-Dist: azure-cosmos; extra == "all"
Requires-Dist: libhoney; extra == "all"
Requires-Dist: influxdb_client; extra == "all"
Requires-Dist: newrelic; extra == "all"
Requires-Dist: aio_statsd; extra == "all"
Requires-Dist: prometheus-client; extra == "all"
Requires-Dist: prometheus-api-client; extra == "all"
Requires-Dist: cassandra-driver; extra == "all"
Requires-Dist: datadog; extra == "all"
Requires-Dist: motor; extra == "all"
Requires-Dist: redis; extra == "all"
Requires-Dist: aioredis; extra == "all"
Requires-Dist: aiomysql; extra == "all"
Requires-Dist: psycopg2-binary; extra == "all"
Requires-Dist: sqlalchemy; extra == "all"
Requires-Dist: sqlalchemy[asyncio]; extra == "all"
Requires-Dist: boto3; extra == "all"
Requires-Dist: snowflake-sqlalchemy; extra == "all"
Requires-Dist: snowflake-connector-python; extra == "all"
Requires-Dist: google-cloud-bigquery; extra == "all"
Requires-Dist: google-cloud-bigtable; extra == "all"
Requires-Dist: google-cloud-storage; extra == "all"
Requires-Dist: cryptography; extra == "all"
Requires-Dist: aioquic; extra == "all"
Requires-Dist: dicttoxml; extra == "all"
Requires-Dist: opentelemetry-api; extra == "all"
Requires-Dist: datadog_api_client; extra == "all"
Requires-Dist: aiokafka; extra == "all"
Requires-Dist: haralyzer; extra == "all"
Requires-Dist: asyncpg; extra == "all"
Requires-Dist: xmltodict; extra == "all"
Provides-Extra: all-clients
Requires-Dist: grpcio; extra == "all-clients"
Requires-Dist: grpcio-tools; extra == "all-clients"
Requires-Dist: gql; extra == "all-clients"
Requires-Dist: playwright; extra == "all-clients"
Requires-Dist: cryptography; extra == "all-clients"
Requires-Dist: aioquic; extra == "all-clients"
Requires-Dist: opentelemetry-api; extra == "all-clients"
Provides-Extra: all-reporters
Requires-Dist: azure-cosmos; extra == "all-reporters"
Requires-Dist: libhoney; extra == "all-reporters"
Requires-Dist: influxdb_client; extra == "all-reporters"
Requires-Dist: newrelic; extra == "all-reporters"
Requires-Dist: aio_statsd; extra == "all-reporters"
Requires-Dist: prometheus-client; extra == "all-reporters"
Requires-Dist: prometheus-api-client; extra == "all-reporters"
Requires-Dist: cassandra-driver; extra == "all-reporters"
Requires-Dist: datadog; extra == "all-reporters"
Requires-Dist: motor; extra == "all-reporters"
Requires-Dist: redis; extra == "all-reporters"
Requires-Dist: aioredis; extra == "all-reporters"
Requires-Dist: aiomysql; extra == "all-reporters"
Requires-Dist: psycopg2-binary; extra == "all-reporters"
Requires-Dist: asyncpg; extra == "all-reporters"
Requires-Dist: sqlalchemy; extra == "all-reporters"
Requires-Dist: boto3; extra == "all-reporters"
Requires-Dist: snowflake-connector-python; extra == "all-reporters"
Requires-Dist: google-cloud-bigquery; extra == "all-reporters"
Requires-Dist: google-cloud-bigtable; extra == "all-reporters"
Requires-Dist: google-cloud-storage; extra == "all-reporters"
Requires-Dist: dicttoxml; extra == "all-reporters"
Requires-Dist: datadog-api-client; extra == "all-reporters"
Requires-Dist: aiosonic; extra == "all-reporters"
Requires-Dist: aiokafka; extra == "all-reporters"
Provides-Extra: playwright
Requires-Dist: playwright; extra == "playwright"
Provides-Extra: azure
Requires-Dist: azure-cosmos; extra == "azure"
Provides-Extra: honeycomb
Requires-Dist: libhoney; extra == "honeycomb"
Provides-Extra: influxdb
Requires-Dist: influxdb_client; extra == "influxdb"
Provides-Extra: newrelic
Requires-Dist: newrelic; extra == "newrelic"
Provides-Extra: statsd
Requires-Dist: aio_statsd; extra == "statsd"
Provides-Extra: prometheus
Requires-Dist: prometheus-client; extra == "prometheus"
Requires-Dist: prometheus-api-client; extra == "prometheus"
Provides-Extra: cassandra
Requires-Dist: cassandra-driver; extra == "cassandra"
Provides-Extra: datadog
Requires-Dist: datadog-api-client; extra == "datadog"
Requires-Dist: aiosonic; extra == "datadog"
Provides-Extra: mongodb
Requires-Dist: motor; extra == "mongodb"
Provides-Extra: redis
Requires-Dist: redis; extra == "redis"
Requires-Dist: aioredis; extra == "redis"
Provides-Extra: kafka
Requires-Dist: aiokafka; extra == "kafka"
Provides-Extra: sql
Requires-Dist: aiomysql; extra == "sql"
Requires-Dist: psycopg2-binary; extra == "sql"
Requires-Dist: asyncpg; extra == "sql"
Requires-Dist: sqlalchemy; extra == "sql"
Requires-Dist: sqlalchemy[asyncio]; extra == "sql"
Provides-Extra: aws
Requires-Dist: boto3; extra == "aws"
Provides-Extra: grpc
Requires-Dist: grpcio; extra == "grpc"
Requires-Dist: grpcio-tools; extra == "grpc"
Provides-Extra: graphql
Requires-Dist: gql; extra == "graphql"
Provides-Extra: http3
Requires-Dist: cryptography; extra == "http3"
Requires-Dist: aioquic; extra == "http3"
Provides-Extra: snowflake
Requires-Dist: snowflake-sqlalchemy; extra == "snowflake"
Requires-Dist: snowflake-connector-python; extra == "snowflake"
Provides-Extra: google
Requires-Dist: google-cloud-bigquery; extra == "google"
Requires-Dist: google-cloud-bigtable; extra == "google"
Requires-Dist: google-cloud-storage; extra == "google"
Provides-Extra: xml
Requires-Dist: dicttoxml; extra == "xml"
Requires-Dist: xmltodict; extra == "xml"
Provides-Extra: opentelemetry
Requires-Dist: opentelemetry-api; extra == "opentelemetry"
Provides-Extra: har
Requires-Dist: haralyzer; extra == "har"
